penny20210731/__init__.py
penny20210731/common_functions.py
penny20210731/lib2.py
penny20210731-0.1.dist-info/METADATA
penny20210731-0.1.dist-info/WHEEL
penny20210731-0.1.dist-info/top_level.txt
penny20210731-0.1.dist-info/RECORD
