Metadata-Version: 2.1
Name: penny20210731
Version: 0.1
Summary: Taiwan No. 1
Home-page: http://github.com/storborg/penny20210731
Author: Michael Chen
Author-email: flyingcircus@example.com
License: MIT
Platform: UNKNOWN
